adept/__init__.py
adept/cli.py
adept/core.py
adept_evo-0.9.6.dist-info/licenses/LICENSE.txt
adept_evo-0.9.6.dist-info/METADATA
adept_evo-0.9.6.dist-info/WHEEL
adept_evo-0.9.6.dist-info/entry_points.txt
adept_evo-0.9.6.dist-info/top_level.txt
adept_evo-0.9.6.dist-info/RECORD
