Metadata-Version: 2.4
Name: adept-evo
Version: 0.9.6
Summary: Automated Dynamics-Aware Evolutionary Profiling Tool (ADEPT)
Home-page: https://github.com/karagol-taner/Dynamics-aware-Evolutionary-Profiling
Author: Taner Karagol
Author-email: taner.karagol@gmail.com
Classifier: Programming Language :: Python :: 3
Classifier: License :: OSI Approved :: MIT License
Classifier: Operating System :: OS Independent
Classifier: Topic :: Scientific/Engineering :: Bio-Informatics
Requires-Python: >=3.7
License-File: LICENSE.txt
Requires-Dist: pandas>=1.0.0
Requires-Dist: numpy>=1.18.0
Dynamic: author
Dynamic: author-email
Dynamic: classifier
Dynamic: description
Dynamic: description-content-type
Dynamic: home-page
Dynamic: license-file
Dynamic: requires-dist
Dynamic: requires-python
Dynamic: summary
